ocp_resources/__init__.py
ocp_resources/api_server.py
ocp_resources/api_service.py
ocp_resources/backup.py
ocp_resources/benchmark.py
ocp_resources/catalog_source.py
ocp_resources/catalog_source_config.py
ocp_resources/cdi.py
ocp_resources/cdi_config.py
ocp_resources/chaos_engine.py
ocp_resources/chaos_result.py
ocp_resources/cluster_operator.py
ocp_resources/cluster_role.py
ocp_resources/cluster_role_binding.py
ocp_resources/cluster_service_version.py
ocp_resources/cluster_version.py
ocp_resources/configmap.py
ocp_resources/console_cli_download.py
ocp_resources/console_plugin.py
ocp_resources/console_quick_start.py
ocp_resources/constants.py
ocp_resources/controller_revision.py
ocp_resources/cron_job.py
ocp_resources/csi_storage_capacity.py
ocp_resources/csidriver.py
ocp_resources/custom_resource_definition.py
ocp_resources/daemonset.py
ocp_resources/data_import_cron.py
ocp_resources/data_source.py
ocp_resources/datavolume.py
ocp_resources/deployment.py
ocp_resources/destination_rule.py
ocp_resources/dns.py
ocp_resources/endpoint_slice.py
ocp_resources/endpoints.py
ocp_resources/event.py
ocp_resources/forklift_controller.py
ocp_resources/gateway.py
ocp_resources/hook.py
ocp_resources/host.py
ocp_resources/hostpath_provisioner.py
ocp_resources/hyperconverged.py
ocp_resources/image.py
ocp_resources/image_content_source_policy.py
ocp_resources/image_stream.py
ocp_resources/imagestreamtag.py
ocp_resources/infrastructure.py
ocp_resources/installplan.py
ocp_resources/ip_address_pool.py
ocp_resources/job.py
ocp_resources/kube_descheduler.py
ocp_resources/kubevirt.py
ocp_resources/kubevirt_common_templates_bundle.py
ocp_resources/kubevirt_metrics_aggregation.py
ocp_resources/kubevirt_node_labeller_bundle.py
ocp_resources/kubevirt_template_validaotr.py
ocp_resources/l2_advertisement.py
ocp_resources/lease.py
ocp_resources/machine.py
ocp_resources/machine_config.py
ocp_resources/machine_config_pool.py
ocp_resources/machine_health_check.py
ocp_resources/machine_set.py
openshift_python_wrapper-4.14.22.dist-info/LICENSE
openshift_python_wrapper-4.14.22.dist-info/METADATA
openshift_python_wrapper-4.14.22.dist-info/WHEEL
openshift_python_wrapper-4.14.22.dist-info/RECORD
