Metadata-Version: 2.1
Name: openshift-python-wrapper
Version: 4.14.22
Summary: Wrapper around https://github.com/openshift/openshift-restclient-python
Home-page: https://github.com/RedHatQE/openshift-python-wrapper
License: Apache-2.0
Keywords: Openshift,Kubevirt,CNV
Author: Meni Yakove
Author-email: myakove@gmail.com
Requires-Python: >=3.8,<4.0
Classifier: License :: OSI Approved :: Apache Software License
Classifier: Operating System :: OS Independent
Classifier: Programming Language :: Python :: 3
Classifier: Programming Language :: Python :: 3.8
Classifier: Programming Language :: Python :: 3.9
Classifier: Programming Language :: Python :: 3.10
Classifier: Programming Language :: Python :: 3.11
Requires-Dist: colorlog (>=6.7.0,<7.0.0)
Requires-Dist: kubernetes (>=27.2.0,<28.0.0)
Requires-Dist: openshift (>=0.13.2,<0.14.0)
Requires-Dist: packaging (>=23.1,<24.0)
Requires-Dist: python-benedict (>=0.32.0,<0.33.0)
Requires-Dist: python-simple-logger (>=1.0.5,<2.0.0)
Requires-Dist: xmltodict (>=0.13.0,<0.14.0)
Project-URL: Bug Tracker, https://github.com/RedHatQE/openshift-python-wrapper/issues
Project-URL: Documentation, https://openshift-python-wrapper.readthedocs.io/en/latest/
Project-URL: Download, https://pypi.org/project/openshift-python-wrapper/
